webdriver/__init__.py
webdriver/driver.py
webdriver/chrome/__init__.py
webdriver/chrome/background_process.py
webdriver/chrome/chrome.py
webdriver/chrome/extension.py
webdriver/chrome/profile.py
webdriver/chrome/window.py
webdriver/components/__init__.py
webdriver/components/element.py
webdriver/gamepad/__init__.py
webdriver/gamepad/gamepad.py
webdriver/gamepad/components/__init__.py
webdriver/gamepad/components/base.py
webdriver/gamepad/components/buttons.py
webdriver/gamepad/components/directional_pad.py
webdriver/gamepad/components/event.py
webdriver/gamepad/components/joystick.py
webdriver/gamepad/components/menu.py
webdriver/gamepad/components/shoulder.py
webdriver/gamepad/xbox/__init__.py
webdriver/gamepad/xbox/xbox.py
browserdriver-0.0.6.dist-info/LICENSE
browserdriver-0.0.6.dist-info/METADATA
browserdriver-0.0.6.dist-info/WHEEL
browserdriver-0.0.6.dist-info/top_level.txt
browserdriver-0.0.6.dist-info/RECORD
